.DS_Store
autogenes/__init__.py
autogenes/core.py
autogenes/ga.py
autogenes/interface.py
autogenes/objectives.py
autogenes-1.0.4.dist-info/LICENSE
autogenes-1.0.4.dist-info/METADATA
autogenes-1.0.4.dist-info/WHEEL
autogenes-1.0.4.dist-info/top_level.txt
autogenes-1.0.4.dist-info/RECORD
