Metadata-Version: 2.1
Name: autogenes
Version: 1.0.4
Summary: Automatic Gene Selection for Bulk Deconvolution
Home-page: https://github.com/theislab/AutoGeneS
Author: Hananeh Aliee, Maxim Schmidt
Author-email: hananeh.aliee@helmholtz-muenchen.de
License: BSD
Platform: UNKNOWN
Classifier: Programming Language :: Python :: 3
Classifier: License :: OSI Approved :: MIT License
Classifier: Operating System :: OS Independent
Requires-Python: >=3.6
Requires-Dist: pandas (>=0.25.1)
Requires-Dist: anndata (>=0.6.22.post1)
Requires-Dist: numpy (>=1.17.2)
Requires-Dist: dill (>=0.3.1.1)
Requires-Dist: deap (>=1.3.0)
Requires-Dist: scipy (>=1.3)
Requires-Dist: cachetools (>=3.1.1)
Requires-Dist: scikit-learn (>=0.21.3)
Requires-Dist: matplotlib (>=3.0.*)
